{
  "variants": {
    "level=0,energized=false,rod_connected=false": {"model": "energized_redstone:block/redstone_holder_0"},
    "level=1,energized=false,rod_connected=false": {"model": "energized_redstone:block/redstone_holder_1"},
    "level=2,energized=false,rod_connected=false": {"model": "energized_redstone:block/redstone_holder_2"},
    "level=3,energized=false,rod_connected=false": {"model": "energized_redstone:block/redstone_holder_3"},
    "level=4,energized=false,rod_connected=false": {"model": "energized_redstone:block/redstone_holder_4"},
    "level=5,energized=false,rod_connected=false": {"model": "energized_redstone:block/redstone_holder_5"},
    "level=6,energized=false,rod_connected=false": {"model": "energized_redstone:block/redstone_holder_6"},
    "level=7,energized=false,rod_connected=false": {"model": "energized_redstone:block/redstone_holder_7"},
    "level=8,energized=false,rod_connected=false": {"model": "energized_redstone:block/redstone_holder_8"},
    "level=9,energized=false,rod_connected=false": {"model": "energized_redstone:block/redstone_holder_9"},
    "level=0,energized=true,rod_connected=false": {"model": "energized_redstone:block/redstone_holder_0_energized"},
    "level=1,energized=true,rod_connected=false": {"model": "energized_redstone:block/redstone_holder_1_energized"},
    "level=2,energized=true,rod_connected=false": {"model": "energized_redstone:block/redstone_holder_2_energized"},
    "level=3,energized=true,rod_connected=false": {"model": "energized_redstone:block/redstone_holder_3_energized"},
    "level=4,energized=true,rod_connected=false": {"model": "energized_redstone:block/redstone_holder_4_energized"},
    "level=5,energized=true,rod_connected=false": {"model": "energized_redstone:block/redstone_holder_5_energized"},
    "level=6,energized=true,rod_connected=false": {"model": "energized_redstone:block/redstone_holder_6_energized"},
    "level=7,energized=true,rod_connected=false": {"model": "energized_redstone:block/redstone_holder_7_energized"},
    "level=8,energized=true,rod_connected=false": {"model": "energized_redstone:block/redstone_holder_8_energized"},
    "level=9,energized=true,rod_connected=false": {"model": "energized_redstone:block/redstone_holder_9_energized"},
    "level=0,energized=false,rod_connected=true": {"model": "energized_redstone:block/redstone_holder_0_connected"},
    "level=1,energized=false,rod_connected=true": {"model": "energized_redstone:block/redstone_holder_1_connected"},
    "level=2,energized=false,rod_connected=true": {"model": "energized_redstone:block/redstone_holder_2_connected"},
    "level=3,energized=false,rod_connected=true": {"model": "energized_redstone:block/redstone_holder_3_connected"},
    "level=4,energized=false,rod_connected=true": {"model": "energized_redstone:block/redstone_holder_4_connected"},
    "level=5,energized=false,rod_connected=true": {"model": "energized_redstone:block/redstone_holder_5_connected"},
    "level=6,energized=false,rod_connected=true": {"model": "energized_redstone:block/redstone_holder_6_connected"},
    "level=7,energized=false,rod_connected=true": {"model": "energized_redstone:block/redstone_holder_7_connected"},
    "level=8,energized=false,rod_connected=true": {"model": "energized_redstone:block/redstone_holder_8_connected"},
    "level=9,energized=false,rod_connected=true": {"model": "energized_redstone:block/redstone_holder_9_connected"},
    "level=0,energized=true,rod_connected=true": {"model": "energized_redstone:block/redstone_holder_0_energized_connected"},
    "level=1,energized=true,rod_connected=true": {"model": "energized_redstone:block/redstone_holder_1_energized_connected"},
    "level=2,energized=true,rod_connected=true": {"model": "energized_redstone:block/redstone_holder_2_energized_connected"},
    "level=3,energized=true,rod_connected=true": {"model": "energized_redstone:block/redstone_holder_3_energized_connected"},
    "level=4,energized=true,rod_connected=true": {"model": "energized_redstone:block/redstone_holder_4_energized_connected"},
    "level=5,energized=true,rod_connected=true": {"model": "energized_redstone:block/redstone_holder_5_energized_connected"},
    "level=6,energized=true,rod_connected=true": {"model": "energized_redstone:block/redstone_holder_6_energized_connected"},
    "level=7,energized=true,rod_connected=true": {"model": "energized_redstone:block/redstone_holder_7_energized_connected"},
    "level=8,energized=true,rod_connected=true": {"model": "energized_redstone:block/redstone_holder_8_energized_connected"},
    "level=9,energized=true,rod_connected=true": {"model": "energized_redstone:block/redstone_holder_9_energized_connected"}
  }
}